luckylog/__init__.py
luckylog/luckylog.py
luckylog-2.0.3.dist-info/LICENSE
luckylog-2.0.3.dist-info/METADATA
luckylog-2.0.3.dist-info/WHEEL
luckylog-2.0.3.dist-info/top_level.txt
luckylog-2.0.3.dist-info/RECORD
