Metadata-Version: 2.1
Name: luckylog
Version: 2.0.3
Summary: 自定义日志模式
Home-page: 
Author: 测码课堂-范晔
Author-email: 1538379200@qq.com
License: UNKNOWN
Platform: UNKNOWN
Classifier: Programming Language :: Python :: 3
Classifier: License :: OSI Approved :: MIT License
Classifier: Operating System :: OS Independent
License-File: LICENSE
